{
  "posts": [
    {
      "id": 1,
      "title": "Услуга",
      "description": "Диагностика зубов и челюстей",
      "price": "3000$"
    },
    {
      "id": 2,
      "title": "Услуга",
      "description": "Диагностика челюстно-лицевой области (ЧЛО), магнитно-резонансная томография (МРТ),электромиография (ЭМГ)",
      "price": "5000$"
    },
    {
      "id": 3,
      "title": "Услуга",
      "description": "Диагностика височно-нижнечелюстных суставов (ВНЧС)",
      "price": "4000$"

    },
    {
      "id": 4,
      "title": "Услуга",
      "description": "Конусно-лучевая компьютерная томография пазух носа,",
      "price": "2500$"

    },
    {
      "id": 5,
      "title": "Услуга",
      "description": "Конусно-лучевая компьютерная томография височной кости",
      "price": "3500$"

    },
    {
      "id": 6,
      "title": "Услуга",
      "description": "Изготовление хирургических навигационных шаблонов для проведения операции имплантации",
      "price": "6000$"

    },
    {
      "id": 7,
      "title": "Услуга",
      "description": "Изготовление элайнеров для проведения ортодонтической коррекции прикуса",
      "price": "4500$"

    },
    {
      "id": 8,
      "title": "Услуга",
      "description": "Центры сканирования полного цикла: рентген, ортодонтический фотопротокол, внутриротовое сканирование, виртуальное планирование",
      "price": "7000$"

    },
    {
      "id": 9,
      "title": "Услуга",
      "description": "Интраоральное сканирование для тех, кто в 3D",
      "price": "3000$"

    },
    {
      "id": 10,
      "title": "Услуга",
      "description": "Ортодонтическое лечение на элайнерах",
      "price": "4000$"

    },
    {
      "id": 11,
      "title": "Услуга",
      "description": "CAD/CAM-моделирование зубного ряда",
      "price": "6500$"

    },
    {
      "id": 12,
      "title": "Услуга",
      "description": "Хирургические направляющие шаблоны — шаг к безупречным результатам имплантации",
      "price": "5000$"

    },
    {
      "id": 13,
      "title": "Услуга",
      "description": "На базе Института дентальной рентгенологии Микеланджело вы можете посетить обучающие курсы по направлениям хирургия и ортодонтия, в том числе семинары по хирургическим шаблонам и ортодонтическим элайнерам.",
      "price": "8000$"

    },
    {
      "id": 14,
      "title": "Услуга",
      "description": "Планирование имплантации с применением хирургических шаблонов",
      "price": "18000$"

    },
    {
      "id": 15,
      "title": "Услуга",
      "description": "Элайнеры «Микеланджело Lab» — Доступная эстетика",
      "price": "1000$"

    },
    {
      "id": 16,
      "title": "Услуга",
      "description": "Мануальная терапия, представляющая собой комплекс мягких и точечных воздействий на ткани и суставы, является исключительным процессом, где искусство лечения сочетается с глубоким пониманием анатомии и физиологии человеческого тела.",
      "price": "9000$"

    },
    {
      "id": 17,
      "title": "Услуга",
      "description": "Иммунизация, наши программы включают в себя полный спектр вакцин, начиная с раннего детства и до пожилого возраста.",
      "price": "12000$"

    }
  ]
}
